LICENSE
MANIFEST.in
README.rst
build_ext.py
conf.py
requirements.txt
setup.cfg
setup.py
examples/cython/build.sh
examples/cython/graph.pyx
examples/cython/run.py
examples/cython/setup.py
mgmetis/__init__.py
mgmetis/enums.py
mgmetis/metis.pxd
mgmetis/metis.py
mgmetis/metis64.pxd
mgmetis/par_utils.py
mgmetis/parmetis.pxd
mgmetis/parmetis.py
mgmetis/parmetis64.pxd
mgmetis/utils.py
mgmetis.egg-info/PKG-INFO
mgmetis.egg-info/SOURCES.txt
mgmetis.egg-info/dependency_links.txt
mgmetis.egg-info/requires.txt
mgmetis.egg-info/top_level.txt
mgmetis/_cython/__init__.py
mgmetis/_cython/impl_metis.pxi
mgmetis/_cython/impl_parmetis.pxi
mgmetis/_cython/metis.pxd
mgmetis/_cython/metis.pyx
mgmetis/_cython/metis64.pxd
mgmetis/_cython/metis64.pyx
mgmetis/_cython/parmetis.pxd
mgmetis/_cython/parmetis.pyx
mgmetis/_cython/parmetis64.pxd
mgmetis/_cython/parmetis64.pyx
mgmetis/src/LICENSE.txt
mgmetis/src/include/parmetis.h
mgmetis/src/libparmetis/akwayfm.c
mgmetis/src/libparmetis/ametis.c
mgmetis/src/libparmetis/balancemylink.c
mgmetis/src/libparmetis/comm.c
mgmetis/src/libparmetis/csrmatch.c
mgmetis/src/libparmetis/ctrl.c
mgmetis/src/libparmetis/debug.c
mgmetis/src/libparmetis/defs.h
mgmetis/src/libparmetis/diffutil.c
mgmetis/src/libparmetis/frename.c
mgmetis/src/libparmetis/gkmetis.c
mgmetis/src/libparmetis/gkmpi.c
mgmetis/src/libparmetis/graph.c
mgmetis/src/libparmetis/initbalance.c
mgmetis/src/libparmetis/initmsection.c
mgmetis/src/libparmetis/initpart.c
mgmetis/src/libparmetis/kmetis.c
mgmetis/src/libparmetis/kwayrefine.c
mgmetis/src/libparmetis/macros.h
mgmetis/src/libparmetis/match.c
mgmetis/src/libparmetis/mdiffusion.c
mgmetis/src/libparmetis/mesh.c
mgmetis/src/libparmetis/mmetis.c
mgmetis/src/libparmetis/move.c
mgmetis/src/libparmetis/msetup.c
mgmetis/src/libparmetis/node_refine.c
mgmetis/src/libparmetis/ometis.c
mgmetis/src/libparmetis/parmetislib.h
mgmetis/src/libparmetis/proto.h
mgmetis/src/libparmetis/pspases.c
mgmetis/src/libparmetis/redomylink.c
mgmetis/src/libparmetis/remap.c
mgmetis/src/libparmetis/rename.h
mgmetis/src/libparmetis/renumber.c
mgmetis/src/libparmetis/rmetis.c
mgmetis/src/libparmetis/selectq.c
