Metadata-Version: 1.2
Name: mgmetis
Version: 0.1.1
Summary: METIS partitioner for mesh and graph
Home-page: https://github.com/chiao45/mgmetis
Author: Qiao Chen
Author-email: benechiao@gmail.com
License: UNKNOWN
Platform: UNKNOWN
Classifier: Development Status :: 3 - Alpha
Classifier: Programming Language :: Python :: 3 :: Only
Classifier: Programming Language :: Python :: 3.6
Classifier: Programming Language :: Python :: 3.7
Classifier: Programming Language :: Python :: 3.8
Classifier: Programming Language :: Cython
Classifier: Programming Language :: C
Classifier: Topic :: Scientific/Engineering
Classifier: Topic :: Scientific/Engineering :: Mathematics
Classifier: Topic :: Software Development
Classifier: Operating System :: Unix
Classifier: Intended Audience :: Science/Research
Classifier: License :: OSI Approved :: MIT License
Requires-Python: >=3.6
